HashedKNN/HashedKNN.py
HashedKNN/__init__.py
HashedKNN-1.0.0.dist-info/LICENSE
HashedKNN-1.0.0.dist-info/METADATA
HashedKNN-1.0.0.dist-info/WHEEL
HashedKNN-1.0.0.dist-info/top_level.txt
HashedKNN-1.0.0.dist-info/RECORD
