Metadata-Version: 2.1
Name: HashedKNN
Version: 1.0.0
Summary: Locality-sensitive hashing to implement K nearesr neighbors fast.
Home-page: https://github.com/MKSHLabs/HashedKNN
Author: Ashish Kashav
Author-email: ashish.kashav1@gmail.com
License: MIT
Keywords: Activity of Daily Living
Platform: UNKNOWN
Classifier: Programming Language :: Python :: 3
Classifier: Development Status :: 3 - Alpha
Classifier: Intended Audience :: Science/Research
Classifier: Intended Audience :: Developers
Classifier: License :: OSI Approved :: MIT License
Classifier: Topic :: Scientific/Engineering :: Artificial Intelligence
Requires-Dist: numpy
Requires-Dist: tqdm
